Python3BasicsTutorial/README.md
Python3BasicsTutorial/__init__.py
Python3BasicsTutorial/__main__.py
Python3BasicsTutorial/file.epub
Python3BasicsTutorial/index.html
Python3BasicsTutorial/css/__init__.py
Python3BasicsTutorial/css/annotations.css
Python3BasicsTutorial/css/main.css
Python3BasicsTutorial/css/normalize.css
Python3BasicsTutorial/css/popup.css
Python3BasicsTutorial/font/__init__.py
Python3BasicsTutorial/font/fontello.eot
Python3BasicsTutorial/font/fontello.svg
Python3BasicsTutorial/font/fontello.ttf
Python3BasicsTutorial/font/fontello.woff
Python3BasicsTutorial/img/__init__.py
Python3BasicsTutorial/img/annotator-glyph-sprite.png
Python3BasicsTutorial/img/annotator-icon-sprite.png
Python3BasicsTutorial/img/apple-touch-icon.png
Python3BasicsTutorial/img/cancelfullscreen.png
Python3BasicsTutorial/img/close.png
Python3BasicsTutorial/img/fullscreen.png
Python3BasicsTutorial/img/loader.gif
Python3BasicsTutorial/img/menu-icon.png
Python3BasicsTutorial/img/save.png
Python3BasicsTutorial/img/saved.png
Python3BasicsTutorial/img/settings-s.png
Python3BasicsTutorial/img/settings.png
Python3BasicsTutorial/img/star.png
Python3BasicsTutorial/js/__init__.py
Python3BasicsTutorial/js/epub.js
Python3BasicsTutorial/js/epub.min.js
Python3BasicsTutorial/js/epub.min.map
Python3BasicsTutorial/js/hooks.min.js
Python3BasicsTutorial/js/hooks.min.map
Python3BasicsTutorial/js/reader.js
Python3BasicsTutorial/js/reader.js.map
Python3BasicsTutorial/js/reader.min.js
Python3BasicsTutorial/js/reader.min.map
Python3BasicsTutorial/js/hooks/__init__.py
Python3BasicsTutorial/js/hooks/extensions/__init__.py
Python3BasicsTutorial/js/hooks/extensions/highlight.js
Python3BasicsTutorial/js/libs/__init__.py
Python3BasicsTutorial/js/libs/jquery.min.js
Python3BasicsTutorial/js/libs/localforage.min.js
Python3BasicsTutorial/js/libs/screenfull.js
Python3BasicsTutorial/js/libs/screenfull.min.js
Python3BasicsTutorial/js/libs/zip.min.js
Python3BasicsTutorial/js/plugins/__init__.py
python_3_basics_tutorial-2024.3.4.0.dist-info/METADATA
python_3_basics_tutorial-2024.3.4.0.dist-info/WHEEL
python_3_basics_tutorial-2024.3.4.0.dist-info/entry_points.txt
python_3_basics_tutorial-2024.3.4.0.dist-info/top_level.txt
python_3_basics_tutorial-2024.3.4.0.dist-info/RECORD
